rich_chat_room/__init__.py
rich_chat_room-0.1.0.dist-info/LICENSE
rich_chat_room-0.1.0.dist-info/METADATA
rich_chat_room-0.1.0.dist-info/WHEEL
rich_chat_room-0.1.0.dist-info/RECORD
